mrsh/__init__.py
mrsh/cli.py
mrsh/core.py
mrsh/libmrsh.so
mrsh/utils.py
mrshw-1.0.0.dist-info/licenses/LICENSE
mrshw-1.0.0.dist-info/METADATA
mrshw-1.0.0.dist-info/WHEEL
mrshw-1.0.0.dist-info/entry_points.txt
mrshw-1.0.0.dist-info/top_level.txt
mrshw-1.0.0.dist-info/RECORD
