Metadata-Version: 2.4
Name: mrshw
Version: 1.0.0
Summary: Python bindings for MRSHv2: modular similarity digest tool for malware analysis, forensics and much more
Home-page: https://github.com/w4term3loon/mrsh
Author: w4term3loon
Author-email: ifkovics.barnabas@gmail.com
Project-URL: Documentation, https://github.com/w4term3loon/mrsh
Project-URL: Source, https://github.com/w4term3loon/mrsh
Project-URL: Bug Tracker, https://github.com/w4term3loon/mrsh/issues
Keywords: binary,analysis,python,binding,malware,hashing,similarity,detection,security,digital,forensics
Classifier: Programming Language :: Python :: 3
Classifier: Programming Language :: C
Classifier: License :: OSI Approved :: MIT License
Classifier: Operating System :: POSIX :: Linux
Classifier: Intended Audience :: Developers
Classifier: Intended Audience :: Information Technology
Classifier: Topic :: Security
Classifier: Topic :: Software Development :: Libraries
Classifier: Topic :: Utilities
Requires-Python: >=3.7
License-File: LICENSE
Dynamic: author
Dynamic: author-email
Dynamic: classifier
Dynamic: description
Dynamic: description-content-type
Dynamic: home-page
Dynamic: keywords
Dynamic: license-file
Dynamic: project-url
Dynamic: requires-python
Dynamic: summary
